ape_base/__init__.py
ape_base/ecosystem.py
ape_base/py.typed
ape_base/version.py
ape_base-0.8.1.dist-info/LICENSE
ape_base-0.8.1.dist-info/METADATA
ape_base-0.8.1.dist-info/WHEEL
ape_base-0.8.1.dist-info/top_level.txt
ape_base-0.8.1.dist-info/RECORD
